{"authorDailyContributionsMap":{"ghos7ie":[{"date":"2024-09-23","commitResults":[{"hash":"c6b009918091e5ad464c3a88989dded90cd75451","isMergeCommit":false,"messageTitle":"Add Remark command","messageBody":"","fileTypesAndContributionMap":{"functional-code":{"insertions":283,"deletions":96},"test-code":{"insertions":238,"deletions":28}}},{"hash":"88f2f7e4af142a82e26560893321a89f5c0672ae","isMergeCommit":false,"messageTitle":"Add EOL","messageBody":"","fileTypesAndContributionMap":{"functional-code":{"insertions":10,"deletions":12},"test-code":{"insertions":6,"deletions":6}}},{"hash":"a7cf40025a0be1403c843cb5ef3b6d0c20c0fda1","isMergeCommit":false,"messageTitle":"Add EOL","messageBody":"","fileTypesAndContributionMap":{"test-code":{"insertions":1,"deletions":1}}},{"hash":"47f9fd4285fba79851e5b48d2e0b3875d904e9ba","isMergeCommit":false,"messageTitle":"Fix checkstyle issues","messageBody":"","fileTypesAndContributionMap":{"functional-code":{"insertions":31,"deletions":26},"test-code":{"insertions":4,"deletions":3}}},{"hash":"98fa304bbd47f091852baa84265764847bfab89c","isMergeCommit":false,"messageTitle":"Fix Test files","messageBody":"","fileTypesAndContributionMap":{"test-code":{"insertions":63,"deletions":146}}},{"hash":"599b1f186240c7475ca668d0c736cf5e9fa50986","isMergeCommit":false,"messageTitle":"Add EOL","messageBody":"","fileTypesAndContributionMap":{"test-code":{"insertions":4,"deletions":4}}}]},{"date":"2024-10-02","commitResults":[{"hash":"cd053ecb1681755db122354ce02b30fde917539b","isMergeCommit":false,"messageTitle":"remove commits from tutorial adding","messageBody":"","fileTypesAndContributionMap":{"functional-code":{"insertions":93,"deletions":283},"test-code":{"insertions":164,"deletions":292}}},{"hash":"d67796536c59b42ec9719c708f16f6264524bee2","isMergeCommit":false,"messageTitle":"Update AboutUs","messageBody":"","fileTypesAndContributionMap":{"docs":{"insertions":4,"deletions":4}}},{"hash":"10a85d8a82e62187490dce911a5d993c76af184f","isMergeCommit":true,"messageTitle":"Merge pull request #17 from YANYAN-w/branch-#14","messageBody":"Update yanyan\u0027s info in AboutUs.md","fileTypesAndContributionMap":{}}]},{"date":"2024-10-03","commitResults":[{"hash":"1e03f3b1fb7db8ca52f0f8d100ba6c9a6005c447","isMergeCommit":false,"messageTitle":"Update DG","messageBody":"","fileTypesAndContributionMap":{"docs":{"insertions":292,"deletions":86}}},{"hash":"2c2376767bc85693d356c5a85165dd19242e5447","isMergeCommit":false,"messageTitle":"Update product scope","messageBody":"","fileTypesAndContributionMap":{"docs":{"insertions":12,"deletions":2}}}]},{"date":"2024-10-04","commitResults":[{"hash":"79c124ba22b8dd44117759cce9e40c634e810c6d","isMergeCommit":false,"messageTitle":"Update readme.md and dg","messageBody":"","fileTypesAndContributionMap":{"docs":{"insertions":19,"deletions":16}}},{"hash":"4168f63358d2df6359a706471157fb52d770b8a0","isMergeCommit":true,"messageTitle":"Merge pull request #34 from ghos7ie/update-readme","messageBody":"Update readme.md and dg","fileTypesAndContributionMap":{}}]},{"date":"2024-10-07","commitResults":[{"hash":"9a6c24d18de65d9b2df2ca11b70394ec61baf364","isMergeCommit":false,"messageTitle":"Rename Person to Student all updated in main folder","messageBody":"","fileTypesAndContributionMap":{"functional-code":{"insertions":214,"deletions":448},"other":{"insertions":98,"deletions":115},"docs":{"insertions":30,"deletions":30},"test-code":{"insertions":184,"deletions":196}}},{"hash":"6bbd9d3b3b9e6600b5a8252c69ab4422a25f8f37","isMergeCommit":false,"messageTitle":"Update JUnit test","messageBody":"","fileTypesAndContributionMap":{"functional-code":{"insertions":33,"deletions":35},"other":{"insertions":6,"deletions":6},"test-code":{"insertions":180,"deletions":547}}},{"hash":"adafe7c0765fc4d7cccc80d229c8e420e41e549f","isMergeCommit":true,"messageTitle":"Merge pull request #37 from ghos7ie/rename-remove","messageBody":"Closes #36","fileTypesAndContributionMap":{}},{"hash":"a4a990c583d755b61ce99b6cbced1a619afda0f1","isMergeCommit":false,"messageTitle":"Fix checkstyle","messageBody":"","fileTypesAndContributionMap":{"functional-code":{"insertions":20,"deletions":16},"test-code":{"insertions":4,"deletions":12}}},{"hash":"12046f083772617a4d22c5242a4615fb67ab4de0","isMergeCommit":true,"messageTitle":"Merge pull request #40 from ghos7ie/rename-remove","messageBody":"Fix checkstyle","fileTypesAndContributionMap":{}}]},{"date":"2024-10-10","commitResults":[{"hash":"d345da05e2254b38577ac73a457ef8b8fcb5972e","isMergeCommit":true,"messageTitle":"Merge pull request #48 from dez2003/add-student","messageBody":"Add Student","fileTypesAndContributionMap":{}}]}],"SooYap":[{"date":"2024-10-02","commitResults":[{"hash":"d3e8e03953102ccf1df328f842428539774e3aee","isMergeCommit":false,"messageTitle":"Update Soo Yap information","messageBody":"","fileTypesAndContributionMap":{"docs":{"insertions":5,"deletions":6}}},{"hash":"05d96815caf1fe22b2f8ab9d7676a12f6195795d","isMergeCommit":true,"messageTitle":"Merge pull request #15 from dez2003/branch-update-aboutus","messageBody":"Update Desiree\u0027s details on AboutUs page","fileTypesAndContributionMap":{}},{"hash":"a1d6e50bdde6cb4a287b42e56a41217063369e6d","isMergeCommit":true,"messageTitle":"Merge branch \u0027master\u0027 of https://github.com/AY2425S1-CS2103-F12-2/tp","messageBody":"","fileTypesAndContributionMap":{}}]},{"date":"2024-10-04","commitResults":[{"hash":"8a4664bdb931714dec1cc8ccbe5a05cdcee9e0fe","isMergeCommit":false,"messageTitle":"Update photo name","messageBody":"","fileTypesAndContributionMap":{"docs":{"insertions":1,"deletions":1}}},{"hash":"9ba059b91209b3ee6b594fd30ed6e2bad2d243bd","isMergeCommit":true,"messageTitle":"Merge pull request #27 from SooYap/Update-Photo","messageBody":"Update SooYap photo","fileTypesAndContributionMap":{}},{"hash":"f3c793fb8bfe5e4dc75a8896af6f0430ef16cbe3","isMergeCommit":true,"messageTitle":"Merge branch \u0027master\u0027 of https://github.com/AY2425S1-CS2103-F12-2/tp","messageBody":"","fileTypesAndContributionMap":{}},{"hash":"f1fdc01a090e0a3d01b91b61f11dc91dfb168e53","isMergeCommit":true,"messageTitle":"Merge pull request #26 from ghos7ie/update-dg","messageBody":"Update DG","fileTypesAndContributionMap":{}},{"hash":"7a32368bad961eeefd60a49a80c31502763590c3","isMergeCommit":true,"messageTitle":"Merge branch \u0027master\u0027 of https://github.com/AY2425S1-CS2103-F12-2/tp","messageBody":"","fileTypesAndContributionMap":{}},{"hash":"56ea28fc3d7ad2401f3e5bea6c1f27df5b865b89","isMergeCommit":false,"messageTitle":"Update Developer Guide with use cases","messageBody":"","fileTypesAndContributionMap":{"docs":{"insertions":130,"deletions":3}}},{"hash":"8493dbec077685550acd8907381f5df0e102fb83","isMergeCommit":true,"messageTitle":"Merge pull request #31 from SooYap/Update-DG","messageBody":"Update DG","fileTypesAndContributionMap":{}}]},{"date":"2024-10-07","commitResults":[{"hash":"086b955dc615c6a7d6244ac7604bf1ba16545d95","isMergeCommit":true,"messageTitle":"Merge branch \u0027master\u0027 of https://github.com/AY2425S1-CS2103-F12-2/tp","messageBody":"","fileTypesAndContributionMap":{}},{"hash":"f93d9778552398ed936f916dd0fdce5bdba8babd","isMergeCommit":false,"messageTitle":"Add optional group field in Student class","messageBody":"","fileTypesAndContributionMap":{"functional-code":{"insertions":15,"deletions":4}}},{"hash":"ecacda6aba7142b9e3fa19df4aeff9181f7d8bb9","isMergeCommit":false,"messageTitle":"Fix syntax errors","messageBody":"","fileTypesAndContributionMap":{"functional-code":{"insertions":1,"deletions":1}}},{"hash":"13c16f4894462b5755e86dacb87f81cd30a90341","isMergeCommit":false,"messageTitle":"Add Javadoc comment to new Student constructor","messageBody":"","fileTypesAndContributionMap":{"functional-code":{"insertions":8,"deletions":1}}},{"hash":"3bc340e59251630a928ddef20f8a93eb5b227a77","isMergeCommit":true,"messageTitle":"Merge pull request #43 from SooYap/update-student-fields","messageBody":"Update student fields","fileTypesAndContributionMap":{}},{"hash":"3f03d57b69798a0500ab7e1bc6d2549f571234c8","isMergeCommit":false,"messageTitle":"Add minimal test cases for new optional group field in Student","messageBody":"","fileTypesAndContributionMap":{"functional-code":{"insertions":1,"deletions":0},"test-code":{"insertions":18,"deletions":2}}},{"hash":"9337c6a5a92c8e6ad06730b71fff3358f9d8f911","isMergeCommit":true,"messageTitle":"Merge pull request #44 from SooYap/update-student-fields","messageBody":"Add minimal test cases for new optional group field in Student","fileTypesAndContributionMap":{}}]},{"date":"2024-10-09","commitResults":[{"hash":"0b3c3f410d79693473b0be0ef18ec928c5eed342","isMergeCommit":true,"messageTitle":"Merge branch \u0027master\u0027 of https://github.com/AY2425S1-CS2103-F12-2/tp","messageBody":"","fileTypesAndContributionMap":{}},{"hash":"9dad478a2f32e6566900639275b3dfb4d961e5e6","isMergeCommit":false,"messageTitle":"Add Group class","messageBody":"","fileTypesAndContributionMap":{"functional-code":{"insertions":170,"deletions":5},"test-code":{"insertions":7,"deletions":3}}},{"hash":"8279f6350d0fdebe57b41a9adf61cf895713b410","isMergeCommit":false,"messageTitle":"Include a UniqueGroupList, AddGroupCommand and AddGroupCommandParser class, and update the relevant fields in ModelManager, ReadOnlyAddressBook, CliSyntax, ParserUtil, and Messages classes to support the new function","messageBody":"","fileTypesAndContributionMap":{"functional-code":{"insertions":398,"deletions":5},"test-code":{"insertions":8,"deletions":8}}}]},{"date":"2024-10-10","commitResults":[{"hash":"b9e1e15581bbd64d87ac9b1503ea10d36b59e751","isMergeCommit":false,"messageTitle":"Correct checkstyle violations","messageBody":"","fileTypesAndContributionMap":{"functional-code":{"insertions":19,"deletions":12}}},{"hash":"d58892412642d2de1493749c67bed311bd810b07","isMergeCommit":false,"messageTitle":"Update test cases to cover the newly added fields","messageBody":"","fileTypesAndContributionMap":{"test-code":{"insertions":30,"deletions":1}}},{"hash":"3f26715ce96b116a99afaa91735ccb5123c96f02","isMergeCommit":false,"messageTitle":"Correct test checkstyle violations","messageBody":"","fileTypesAndContributionMap":{"test-code":{"insertions":3,"deletions":3}}},{"hash":"f3dd881071dee4c669969732b75b26764f80fc1e","isMergeCommit":false,"messageTitle":"Implement storage saving functionality for adding groups","messageBody":"","fileTypesAndContributionMap":{"functional-code":{"insertions":100,"deletions":3}}},{"hash":"9c0fabac77ca948c477e4c6dda7483877650b6d3","isMergeCommit":false,"messageTitle":"Fix error message which displays upon user entering an invalid group name","messageBody":"","fileTypesAndContributionMap":{"functional-code":{"insertions":5,"deletions":7}}},{"hash":"9394f64353154b81d858311cf0897dcd759bbb70","isMergeCommit":false,"messageTitle":"Update JUnit tests","messageBody":"","fileTypesAndContributionMap":{"functional-code":{"insertions":14,"deletions":2},"test-code":{"insertions":421,"deletions":0}}},{"hash":"80814164b076741d1d0c4b40c88d27fe649fceaf","isMergeCommit":true,"messageTitle":"Merge branch \u0027master\u0027 of https://github.com/AY2425S1-CS2103-F12-2/tp","messageBody":"","fileTypesAndContributionMap":{}},{"hash":"438dc11a07fa9b0993d49574fc10007f4abd7bf9","isMergeCommit":true,"messageTitle":"Merge branch \u0027create-group-class\u0027","messageBody":"# Conflicts:\n#\tsrc/test/data/JsonSerializableAddressBookTest/duplicatePersonAddressBook.json\n#\tsrc/test/data/JsonSerializableAddressBookTest/typicalPersonsAddressBook.json\n#\tsrc/test/java/seedu/address/logic/commands/CommandTestUtil.java\n","fileTypesAndContributionMap":{}},{"hash":"7d0a0886c8a39544e0d50d0d1ecf285cab98c3e3","isMergeCommit":true,"messageTitle":"Merge pull request #52 from SooYap/master","messageBody":"Add Student and Add Group Functionality","fileTypesAndContributionMap":{}},{"hash":"4ae35a31cf3b65762c3e6025aee99e9e573fe372","isMergeCommit":true,"messageTitle":"Merge branch \u0027master\u0027 into branch-delete-student","messageBody":"","fileTypesAndContributionMap":{}},{"hash":"fed9d9d637af7565a8062429c51bc67377191eae","isMergeCommit":true,"messageTitle":"Merge pull request #49 from YANYAN-w/branch-delete-student","messageBody":"Refactored DeleteCommand to DeleteStudentCommand","fileTypesAndContributionMap":{}},{"hash":"bacf4fba1d6a4ba1b66386d77fb4e6c696efc7c5","isMergeCommit":true,"messageTitle":"Merge branch \u0027master\u0027 of https://github.com/AY2425S1-CS2103-F12-2/tp","messageBody":"","fileTypesAndContributionMap":{}},{"hash":"60698b9cfabee2b27e6e99943696fcc329badc88","isMergeCommit":false,"messageTitle":"Fix bugs","messageBody":"","fileTypesAndContributionMap":{"functional-code":{"insertions":1,"deletions":32}}}]},{"date":"2024-10-11","commitResults":[{"hash":"bd6aaaebad06b381aaa107c03b5b9bf4956d296b","isMergeCommit":false,"messageTitle":"Fix JUnit test cases","messageBody":"","fileTypesAndContributionMap":{"functional-code":{"insertions":39,"deletions":120},"other":{"insertions":8,"deletions":7},"test-code":{"insertions":20,"deletions":139}}},{"hash":"c1a947915ae8e986c1b731c2979f6f997b6ddefc","isMergeCommit":true,"messageTitle":"Merge pull request #53 from SooYap/remove-current-bugs","messageBody":"Remove current bugs","fileTypesAndContributionMap":{}}]}],"YANYAN-w":[{"date":"2024-10-02","commitResults":[{"hash":"f02fe3b9de4b9ab7e6f73d58fa17286a11a6cde1","isMergeCommit":false,"messageTitle":"Update AboutUs.md","messageBody":"","fileTypesAndContributionMap":{"docs":{"insertions":7,"deletions":7}}},{"hash":"fa6e8ff4f450ce88aaa6fcc798d9046273ef2303","isMergeCommit":false,"messageTitle":"Update AboutUs.md","messageBody":"","fileTypesAndContributionMap":{"docs":{"insertions":3,"deletions":2}}},{"hash":"7a45d6c21a38d1f44c595d5c2451f25506ed9778","isMergeCommit":true,"messageTitle":"Merge branch \u0027master\u0027 into update-lewis-aboutus","messageBody":"","fileTypesAndContributionMap":{}},{"hash":"53f4d21ace3136fee65e764e3746a3d8c1796a38","isMergeCommit":true,"messageTitle":"Merge pull request #18 from ghos7ie/update-lewis-aboutus","messageBody":"Update AboutUs","fileTypesAndContributionMap":{}}]},{"date":"2024-10-03","commitResults":[{"hash":"bd338ec5ace4e3d80a50c54181fdf481a72e527c","isMergeCommit":false,"messageTitle":"Update README.md","messageBody":"","fileTypesAndContributionMap":{"docs":{"insertions":4,"deletions":3}}},{"hash":"9116dedd5e4ff95ed3aa78f6572f9102a1d0887c","isMergeCommit":true,"messageTitle":"Merge pull request #23 from YANYAN-w/branch-A","messageBody":"Update README.md","fileTypesAndContributionMap":{}},{"hash":"5b59b1f35b0cb35df6ff182a50b778abf89a6927","isMergeCommit":true,"messageTitle":"Merge pull request #25 from YANYAN-w/branch-A","messageBody":"Update README and Ui image","fileTypesAndContributionMap":{}}]},{"date":"2024-10-04","commitResults":[{"hash":"7b08e60b9b674e8360c1521962ee25c8643769a5","isMergeCommit":false,"messageTitle":"Update README.md","messageBody":"","fileTypesAndContributionMap":{"docs":{"insertions":4,"deletions":6}}},{"hash":"7fcccd8919051b2d02eaf64afbec9a8338a0d962","isMergeCommit":true,"messageTitle":"Merge pull request #28 from YANYAN-w/branch-A","messageBody":"Update README.md","fileTypesAndContributionMap":{}}]},{"date":"2024-10-09","commitResults":[{"hash":"e805953fc4b098faa77b871a482c51c2db5d111f","isMergeCommit":false,"messageTitle":"refactored DeleteCommand to DeleteStudentCommand, updated the test cases","messageBody":"","fileTypesAndContributionMap":{"functional-code":{"insertions":258,"deletions":27},"test-code":{"insertions":98,"deletions":4}}}]},{"date":"2024-10-10","commitResults":[{"hash":"14c9b89793a2054cd6251371675cccd0ac9ea720","isMergeCommit":true,"messageTitle":"Merge branch \u0027create-group-class\u0027 of https://github.com/SooYap/tp into SooYap-create-group-class","messageBody":"","fileTypesAndContributionMap":{}},{"hash":"81597ee6c0a131e58867812a9dcef96f02cc8137","isMergeCommit":true,"messageTitle":"Merge branch \u0027SooYap-create-group-class\u0027","messageBody":"","fileTypesAndContributionMap":{}}]}],"dez2003":[{"date":"2024-10-02","commitResults":[{"hash":"cef679ad04a1d10e3d0863011036ce737c5c8799","isMergeCommit":false,"messageTitle":"Update Desiree\u0027s details on AboutUs page","messageBody":"","fileTypesAndContributionMap":{"docs":{"insertions":4,"deletions":15}}},{"hash":"ddf4bc2806d8c4627280b0e07bd4378734af57a8","isMergeCommit":true,"messageTitle":"Merge branch \u0027master\u0027 into Update-AboutUs","messageBody":"","fileTypesAndContributionMap":{}},{"hash":"6f9f87d4462c06013b2831c09c3fadc80a95ac2b","isMergeCommit":true,"messageTitle":"Merge pull request #16 from SooYap/Update-AboutUs","messageBody":"Update Soo Yap information","fileTypesAndContributionMap":{}}]},{"date":"2024-10-04","commitResults":[{"hash":"3252f23ad23eea007cd78c6b393f0b42ce693a6d","isMergeCommit":false,"messageTitle":"Update site-wide settings using MarkBind","messageBody":"Renamed AB-3 with T_Assistant across all site pages, and removed\nplaceholder in AboutUs page.\n","fileTypesAndContributionMap":{"docs":{"insertions":7,"deletions":17}}},{"hash":"153915705ae5b94ab7738efb0c5c1d17b6b957ae","isMergeCommit":true,"messageTitle":"Merge pull request #32 from dez2003/branch-B","messageBody":"Update site-wide settings using MarkBind","fileTypesAndContributionMap":{}}]},{"date":"2024-10-09","commitResults":[{"hash":"682f5c7ab6bea03e164621ec08b10136e98572e1","isMergeCommit":false,"messageTitle":"Add studentNumber field to Student class","messageBody":"The Student class doesn\u0027t have a student number field, which is\nconsidered important information to have for tutors to uniquely\nidentify each student.\n\nLet\u0027s add a student number field and update other classes\nwhere necessary.\n","fileTypesAndContributionMap":{"functional-code":{"insertions":74,"deletions":6},"test-code":{"insertions":14,"deletions":1}}},{"hash":"cbce0f810453ec0ddc3557d0af6db977e7b4c666","isMergeCommit":false,"messageTitle":"Update Parser and AddCommand and its related classes","messageBody":"The parser and add command doesn\u0027t take into account the new argument\nstudent number when adding a new student to the system since it was a\nnew field added for Student class.\n\nLet\u0027s\n* add the student number prefix and rename the student name prefix\n* add the argument student number to AddCommand\n* implement the prefixes into the parser, command, and test classes\n* rename the command word to \"add_student\"\n","fileTypesAndContributionMap":{"functional-code":{"insertions":58,"deletions":22},"test-code":{"insertions":39,"deletions":22}}},{"hash":"3857e0df83268a63b54fc15bbb288750f501a05d","isMergeCommit":false,"messageTitle":"Modify GUI to show student number","messageBody":"","fileTypesAndContributionMap":{"functional-code":{"insertions":28,"deletions":10},"test-code":{"insertions":6,"deletions":7}}},{"hash":"c7cb20619af3ca4d58fe8824be5ff5c4bbb364d2","isMergeCommit":false,"messageTitle":"Refactor AddCommand class to AddStudentCommand","messageBody":"The class name AddCommand is too general since there\u0027ll be another\nfeature that will be adding groups.\n\nTo make the command more specific and easier to understand, let\u0027s\nrename the class name to AddStudentCommand and rename other related\nclass\u0027 names.\n","fileTypesAndContributionMap":{"functional-code":{"insertions":3,"deletions":3},"other":{"insertions":38,"deletions":38},"test-code":{"insertions":8,"deletions":8}}},{"hash":"016be2c20c514ed4812e66d29d9dea9d3eaaeef8","isMergeCommit":false,"messageTitle":"Fix checkstyle issues","messageBody":"","fileTypesAndContributionMap":{"functional-code":{"insertions":17,"deletions":8},"test-code":{"insertions":2,"deletions":1}}},{"hash":"28e2c5b69856aa5e51a51930440170c2adeec41e","isMergeCommit":false,"messageTitle":"Add JavaDoc comment to StudentNumber class","messageBody":"","fileTypesAndContributionMap":{"functional-code":{"insertions":6,"deletions":6}}},{"hash":"cfdaba6eb75d19c6033f2fbab8b7a6b4a956b76c","isMergeCommit":false,"messageTitle":"Fix more checkstyle issues","messageBody":"","fileTypesAndContributionMap":{"test-code":{"insertions":13,"deletions":6}}}]},{"date":"2024-10-10","commitResults":[{"hash":"2b9de41f0ce9384333acf6a714b2e8badcb48d5b","isMergeCommit":false,"messageTitle":"Update code to pass all tests","messageBody":"","fileTypesAndContributionMap":{"functional-code":{"insertions":21,"deletions":9},"test-code":{"insertions":52,"deletions":31}}}]}]},"authorFileTypeContributionMap":{"ghos7ie":{"docs":325,"functional-code":253,"test-code":279},"SooYap":{"docs":134,"functional-code":717,"test-code":483},"YANYAN-w":{"docs":7,"functional-code":148,"test-code":96},"dez2003":{"docs":11,"functional-code":139,"test-code":121}},"authorContributionVariance":{"ghos7ie":255954.94,"SooYap":35359.445,"YANYAN-w":6461.1763,"dez2003":8839.926},"authorDisplayNameMap":{"ghos7ie":"CS2103-F12-2 LYE ..EWIS","SooYap":"CS2103-F12-2 TAN .. YAP","YANYAN-w":"CS2103-F12-2 WANG..NYAN","dez2003":"CS2103-F12-2 SNG ..IREE"}}
