{"authorDailyContributionsMap":{"SlothyCat":[{"date":"2024-10-01","commitResults":[{"hash":"ed3940664742c687c162d327079689df1e1d711b","isMergeCommit":false,"messageTitle":"Update AboutUs.md","messageBody":"","fileTypesAndContributionMap":{"docs":{"insertions":5,"deletions":6}}},{"hash":"1bbc331f26c1e1a17973112a11952c270c39c7ce","isMergeCommit":true,"messageTitle":"Merge branch \u0027master\u0027 into update-about-us","messageBody":"","fileTypesAndContributionMap":{}},{"hash":"936cc332851a125516108fc0be31f31b9a41f444","isMergeCommit":true,"messageTitle":"Merge pull request #30 from SlothyCat/update-about-us","messageBody":"Update AboutUs.md","fileTypesAndContributionMap":{}},{"hash":"d5e4fa52968cdb6401d9a879816d45a61086e588","isMergeCommit":false,"messageTitle":"Update README.md","messageBody":"","fileTypesAndContributionMap":{"docs":{"insertions":7,"deletions":6}}},{"hash":"e8879e8b9416f47559a6806e5b3339e450ce7c6a","isMergeCommit":false,"messageTitle":"Add details to README","messageBody":"","fileTypesAndContributionMap":{"docs":{"insertions":1,"deletions":1}}}]},{"date":"2024-10-02","commitResults":[{"hash":"82caba5534879e1bff4f447a46a2338a0292db28","isMergeCommit":false,"messageTitle":"Update photo name to lowercase","messageBody":"","fileTypesAndContributionMap":{"docs":{"insertions":1,"deletions":1}}},{"hash":"2ef517a1e9bea1587205918ed277b48297f6b562","isMergeCommit":true,"messageTitle":"Merge pull request #45 from SlothyCat/adding-photo","messageBody":"Update photo name to lowercase","fileTypesAndContributionMap":{}}]},{"date":"2024-10-05","commitResults":[{"hash":"a1e605124905cffa7effb84f422d83ccb03d79a0","isMergeCommit":false,"messageTitle":"Update README.md","messageBody":"","fileTypesAndContributionMap":{"docs":{"insertions":2,"deletions":2}}},{"hash":"3619b2fb79f9d4e7a3c7e8a6b3114d6b9f9cb2ae","isMergeCommit":true,"messageTitle":"Merge pull request #41 from SlothyCat/update-ui-photo","messageBody":"Update README.md","fileTypesAndContributionMap":{}}]},{"date":"2024-10-09","commitResults":[{"hash":"50a73e432b5538ccf589755d91e37dbfb16f3d9a","isMergeCommit":false,"messageTitle":"Create Light Theme","messageBody":"","fileTypesAndContributionMap":{"functional-code":{"insertions":356,"deletions":2}}}]},{"date":"2024-10-10","commitResults":[{"hash":"7c4d4eecace68ee444fb10df0f8b3c1e7d186bc7","isMergeCommit":false,"messageTitle":"Update DarkTheme to be default","messageBody":"","fileTypesAndContributionMap":{"functional-code":{"insertions":4,"deletions":3}}},{"hash":"5732902de6d117d39ca93656add7ee5a1d04f406","isMergeCommit":true,"messageTitle":"Merge pull request #52 from SlothyCat/upgrade-gui","messageBody":"Create Light Theme","fileTypesAndContributionMap":{}}]},{"date":"2024-10-11","commitResults":[{"hash":"5f322bd72cec211f90b426ca8f31854995b28b11","isMergeCommit":true,"messageTitle":"Merge pull request #59 from kimberlytmq/Add-Telegram-Handle","messageBody":"Add telegram handle feature","fileTypesAndContributionMap":{}},{"hash":"de9487a1c96633b3aef29ebfa28799d46c97e8bf","isMergeCommit":true,"messageTitle":"Merge pull request #62 from zienxu/branch-FilterContactTypeCommand","messageBody":"Add FilterContactTypeCommand class and ContactTypePredicate class","fileTypesAndContributionMap":{}}]},{"date":"2024-10-17","commitResults":[{"hash":"a87ef9744ff75469dc94f5f07ced1df9507a895b","isMergeCommit":false,"messageTitle":"Update Find Feature for Telegram Handle","messageBody":"","fileTypesAndContributionMap":{"functional-code":{"insertions":73,"deletions":12},"test-code":{"insertions":25,"deletions":3}}},{"hash":"e2ae31ecdfb17b9e8d23377ed389f3c44fe4c863","isMergeCommit":false,"messageTitle":"Fix code to adhere to Coding Standards","messageBody":"","fileTypesAndContributionMap":{"functional-code":{"insertions":2,"deletions":2},"test-code":{"insertions":2,"deletions":2}}},{"hash":"869d3ab627c91e7e42c8536da178a462ec3be639","isMergeCommit":true,"messageTitle":"Merge pull request #73 from achl1012/update-edit-command","messageBody":"Update edit and add command","fileTypesAndContributionMap":{}},{"hash":"41e2f76e1252223b615bfaeff88d0c5cbf253e37","isMergeCommit":true,"messageTitle":"Merge pull request #74 from SlothyCat/update-find-feature","messageBody":"Update Find Feature for Telegram Handle","fileTypesAndContributionMap":{}},{"hash":"f3c1f382ca2967a1f7555774a27261c08dc2e81c","isMergeCommit":false,"messageTitle":"Update Dark Theme","messageBody":"","fileTypesAndContributionMap":{"functional-code":{"insertions":84,"deletions":34}}},{"hash":"665ee127de59634e0feb6c19540d9b7c8f2d36d8","isMergeCommit":true,"messageTitle":"Merge pull request #79 from SlothyCat/improve-dark-theme","messageBody":"Update Dark Theme","tags":["v1.3"],"fileTypesAndContributionMap":{}}]}],"zienxu":[{"date":"2024-10-01","commitResults":[{"hash":"13f2ff0e9f92917377bd4a844ed473ee0197eb83","isMergeCommit":false,"messageTitle":"Update AboutUs.md","messageBody":"","fileTypesAndContributionMap":{"docs":{"insertions":5,"deletions":6}}},{"hash":"ec95bf6b1dae0b5ee52a02f352b8ed53764ea40f","isMergeCommit":true,"messageTitle":"Merge pull request #27 from zienxu/update-about-us","messageBody":"Update AboutUs.md","fileTypesAndContributionMap":{}}]},{"date":"2024-10-02","commitResults":[{"hash":"2a397cc788866d69e66df2ea6cee9f8f31f06799","isMergeCommit":false,"messageTitle":"Add non-functional requirements","messageBody":"","fileTypesAndContributionMap":{"docs":{"insertions":8,"deletions":3}}}]},{"date":"2024-10-03","commitResults":[{"hash":"f5018ec10aa8c10f4feecfe0fe4b334bc9ae3037","isMergeCommit":false,"messageTitle":"Update docs/DeveloperGuide.md","messageBody":"Co-authored-by: Yatoo \u003c121914292+jtooya@users.noreply.github.com\u003e","fileTypesAndContributionMap":{"docs":{"insertions":1,"deletions":1}}},{"hash":"acb67a2862a4636919012fd24e215789bc9a3f72","isMergeCommit":false,"messageTitle":"Update NFRs for DeveloperGuide","messageBody":"","fileTypesAndContributionMap":{"docs":{"insertions":7,"deletions":8}}},{"hash":"70e3643612e6dc8daf2f6ae8f43f44edc4c0c1ed","isMergeCommit":true,"messageTitle":"Update NFR","messageBody":"","fileTypesAndContributionMap":{}}]},{"date":"2024-10-05","commitResults":[{"hash":"35a71fccaf3390b9bc9d11c971a0947a5153ba01","isMergeCommit":true,"messageTitle":"Merge pull request #42 from zienxu/branch-nfr","messageBody":"Add non-functional requirements","fileTypesAndContributionMap":{}}]},{"date":"2024-10-11","commitResults":[{"hash":"5d92ef48dee779c706cc63111b6b82da099ff33d","isMergeCommit":false,"messageTitle":"Add FilterContactTypeCommand class and ContactTypePredicate class","messageBody":"","fileTypesAndContributionMap":{"functional-code":{"insertions":103,"deletions":0}}},{"hash":"6d6518fe4845a29ed4fbe5df49aea4ab05f6a3e5","isMergeCommit":false,"messageTitle":"Add Javadoc commments for FilterContactTypeCommand class and ContactTypePredicate class","messageBody":"","fileTypesAndContributionMap":{"functional-code":{"insertions":17,"deletions":1}}},{"hash":"14ee42234de58d2d6cd343643630b032a5cc9467","isMergeCommit":false,"messageTitle":"Add Javadoc commments for FilterContactTypeCommand class","messageBody":"","fileTypesAndContributionMap":{"functional-code":{"insertions":4,"deletions":0}}}]},{"date":"2024-10-16","commitResults":[{"hash":"1233f45b253dc1cb2ab37a63bf27cbcbd0a9bae8","isMergeCommit":false,"messageTitle":"Add FilterContactTypeParser class","messageBody":"Add PREFIX_CONTACTTYPE in CliSyntax.java\nAdd ContactTypeParser method in ParserUtil.java\nAdd ContactType field and getContactType() method in Person.java\n","fileTypesAndContributionMap":{"functional-code":{"insertions":50,"deletions":6}}},{"hash":"a5c37c204462264577c55e11410fed3f072ef286","isMergeCommit":false,"messageTitle":"Debug code to ensure FilterContactTypeCommand works","messageBody":"","fileTypesAndContributionMap":{"functional-code":{"insertions":30,"deletions":12},"other":{"insertions":1,"deletions":1}}},{"hash":"0dd271acdfe95c921d8583f672e404717814c53a","isMergeCommit":false,"messageTitle":"Fix syntax error for build (macos-latest)","messageBody":"","fileTypesAndContributionMap":{"functional-code":{"insertions":18,"deletions":13}}},{"hash":"1746d7a92e0fa935012fd02639d05a95ab26f221","isMergeCommit":false,"messageTitle":"Edit PersonBuilder.java to include ContactType field","messageBody":"","fileTypesAndContributionMap":{"test-code":{"insertions":13,"deletions":1}}}]}],"jtooya":[{"date":"2024-10-01","commitResults":[{"hash":"b705780304f2a235d5b6e3448291382c6fdd0ec2","isMergeCommit":false,"messageTitle":"Update AboutUs.md","messageBody":"","fileTypesAndContributionMap":{"docs":{"insertions":6,"deletions":7}}},{"hash":"eec3eb7a88261d5bacb5878451f5d5047f46a1f4","isMergeCommit":true,"messageTitle":"Merge pull request #26 from jtooya/update-AboutUs","messageBody":"Update AboutUs.md","fileTypesAndContributionMap":{}}]},{"date":"2024-10-04","commitResults":[{"hash":"d7f27c7fcd092c410601b5b96a098cf30f5776df","isMergeCommit":false,"messageTitle":"Update glossary","messageBody":"","fileTypesAndContributionMap":{"docs":{"insertions":2,"deletions":0}}}]},{"date":"2024-10-09","commitResults":[{"hash":"ed8d6e59ad418112eb6c4159812948b1cf4b12d4","isMergeCommit":true,"messageTitle":"Merge pull request #50 from jtooya/update-Glossary","messageBody":"Update glossary","fileTypesAndContributionMap":{}}]},{"date":"2024-10-10","commitResults":[{"hash":"8559503aceaec525489edac89a12072bd2601a6b","isMergeCommit":false,"messageTitle":"Add ContactType class and corresponding enum","messageBody":"","fileTypesAndContributionMap":{"functional-code":{"insertions":63,"deletions":0}}},{"hash":"a9c4efc1f290dc07ada1157508ebd9e63932241a","isMergeCommit":false,"messageTitle":"Fix checkstyle errors","messageBody":"","fileTypesAndContributionMap":{"functional-code":{"insertions":11,"deletions":2}}},{"hash":"a5f3650a79371315438537cc1863a98b3c6bf481","isMergeCommit":true,"messageTitle":"Merge pull request #56 from jtooya/add-contact-type","messageBody":"Add ContactType class and corresponding enum","fileTypesAndContributionMap":{}}]},{"date":"2024-10-17","commitResults":[{"hash":"6eeb15c8eb5074fce6d4d4cc7247c2147e003dcf","isMergeCommit":true,"messageTitle":"Merge branch \u0027ContactTypeToParser\u0027 of https://github.com/zienxu/tp into ContactTypeToParser","messageBody":"","fileTypesAndContributionMap":{}},{"hash":"e3393188a8491f64856e26a6826f88ff45f5ad2a","isMergeCommit":false,"messageTitle":"Fix bug in EditCommand","messageBody":"","fileTypesAndContributionMap":{"functional-code":{"insertions":1,"deletions":2}}},{"hash":"2551052342ad9b3654ff64beddc6e3ebf4b2c1d0","isMergeCommit":false,"messageTitle":"Fix bugs in contactType implementation","messageBody":"","fileTypesAndContributionMap":{"functional-code":{"insertions":19,"deletions":13},"test-code":{"insertions":42,"deletions":24}}},{"hash":"7193e5c320bd12e860e0b8fdca353a0898d2ace3","isMergeCommit":false,"messageTitle":"Fix checkstyle errors","messageBody":"","fileTypesAndContributionMap":{"test-code":{"insertions":9,"deletions":10}}},{"hash":"1533f3a35dd8db135820c6db162ced0bf30c889b","isMergeCommit":true,"messageTitle":"Merge pull request #75 from jtooya/ContactTypeToParser","messageBody":"Contact type to parser","fileTypesAndContributionMap":{}},{"hash":"155f6aa97e7c663ffe09f287d1271becde56c931","isMergeCommit":false,"messageTitle":"Fix error message for addcommand","messageBody":"","fileTypesAndContributionMap":{"functional-code":{"insertions":4,"deletions":3}}},{"hash":"002964f88f1c2e9fc07228ba9676957f7742f78d","isMergeCommit":false,"messageTitle":"Revert GUI to dark mode","messageBody":"","fileTypesAndContributionMap":{"functional-code":{"insertions":1,"deletions":1}}}]}],"achl1012":[{"date":"2024-09-22","commitResults":[{"hash":"ebfabc1c6e3229880125f29726aa83b27e468b9f","isMergeCommit":false,"messageTitle":"Update site configs","messageBody":"","fileTypesAndContributionMap":{"docs":{"insertions":1,"deletions":1}}},{"hash":"2ec5848964fb6bd85133ac5f03f20be69a9d2a1f","isMergeCommit":true,"messageTitle":"Merge pull request #2 from achl1012/master","messageBody":"Update site configs","fileTypesAndContributionMap":{}}]},{"date":"2024-10-01","commitResults":[{"hash":"e118d806683b8b71d993a035fc4c8c8324de9390","isMergeCommit":false,"messageTitle":"Update AboutUs","messageBody":"","fileTypesAndContributionMap":{"docs":{"insertions":5,"deletions":6}}},{"hash":"1f9c16ebc3eb5a9f248c536ca763b8202a11fed6","isMergeCommit":true,"messageTitle":"Merge pull request #28 from achl1012/update-aboutus","messageBody":"Update AboutUs","fileTypesAndContributionMap":{}}]},{"date":"2024-10-03","commitResults":[{"hash":"87b0fc982d2d630d3ddd11ba06cfdc4729feefbe","isMergeCommit":false,"messageTitle":"Add use cases to developer guide","messageBody":"","fileTypesAndContributionMap":{"docs":{"insertions":85,"deletions":6}}},{"hash":"f340bbfa583b8d6f0226f993e36ae4f792ad384e","isMergeCommit":false,"messageTitle":"Edit use cases","messageBody":"","fileTypesAndContributionMap":{"docs":{"insertions":1,"deletions":1}}}]},{"date":"2024-10-05","commitResults":[{"hash":"172fafc9556242bf7265e7a230573636db016e3d","isMergeCommit":true,"messageTitle":"Merge pull request #47 from achl1012/update-DG","messageBody":"Add use cases to developer guide","fileTypesAndContributionMap":{}}]},{"date":"2024-10-10","commitResults":[{"hash":"f4345ca902fb722ef22195f572f724e8107ae48f","isMergeCommit":false,"messageTitle":"Remove address field and its usages","messageBody":"","fileTypesAndContributionMap":{"functional-code":{"insertions":16,"deletions":154},"test-code":{"insertions":56,"deletions":241}}},{"hash":"e75cd2027269bb54f46813a81180f5a638c31cc6","isMergeCommit":false,"messageTitle":"Make minor edits","messageBody":"","fileTypesAndContributionMap":{"functional-code":{"insertions":1,"deletions":2},"test-code":{"insertions":2,"deletions":1}}},{"hash":"b307b85fd48a044241e135b41ba0562a69647722","isMergeCommit":true,"messageTitle":"Merge pull request #57 from achl1012/delete-address","messageBody":"Remove address field and its usages","fileTypesAndContributionMap":{}}]},{"date":"2024-10-15","commitResults":[{"hash":"b03ad0c1c768e34fdd202c8cdfd4808f4b08bcc7","isMergeCommit":true,"messageTitle":"Merge pull request #67 from kimberlytmq/Improve-telegram-handle","messageBody":"Improve telegram handle","fileTypesAndContributionMap":{}}]},{"date":"2024-10-16","commitResults":[{"hash":"000d4a99d7b0da7d3c20ee0706bf62d30996e9e3","isMergeCommit":false,"messageTitle":"Add telegram handle to edit command","messageBody":"","fileTypesAndContributionMap":{"functional-code":{"insertions":24,"deletions":6}}},{"hash":"7b65d37134e5559c954d3bc37b951d38eb29c091","isMergeCommit":false,"messageTitle":"Add tests for TelegramHandle field","messageBody":"","fileTypesAndContributionMap":{"functional-code":{"insertions":21,"deletions":8},"test-code":{"insertions":206,"deletions":34}}},{"hash":"e527f639c8abec69cac92a4e8ea572ccf01165df","isMergeCommit":false,"messageTitle":"Include telegram handle in add command","messageBody":"","fileTypesAndContributionMap":{"functional-code":{"insertions":10,"deletions":4}}}]},{"date":"2024-10-17","commitResults":[{"hash":"225c3acd9fe6136d4abf41446102fbb32ba48c35","isMergeCommit":false,"messageTitle":"Update tests related to add command","messageBody":"","fileTypesAndContributionMap":{"test-code":{"insertions":43,"deletions":23}}},{"hash":"5a23c1603bc6f2cdc3b35ffc7781778707237e3b","isMergeCommit":false,"messageTitle":"Fix checkstyle issues","messageBody":"","fileTypesAndContributionMap":{"functional-code":{"insertions":4,"deletions":2}}},{"hash":"4ff64f81e3de0b46d30ef3b520bd791862144804","isMergeCommit":false,"messageTitle":"Fix checkstyle errors in tests","messageBody":"","fileTypesAndContributionMap":{"test-code":{"insertions":27,"deletions":12}}},{"hash":"dc25e3200d2cb38b66e0b614f3b2e37075e664d2","isMergeCommit":true,"messageTitle":"Merge pull request #77 from jtooya/ContactTypeToParser","messageBody":"Fix error message for addcommand","fileTypesAndContributionMap":{}}]}],"kimberlytmq":[{"date":"2024-10-01","commitResults":[{"hash":"1b5a96cf86bc27f0254e018c75a2f1e88ee8c596","isMergeCommit":false,"messageTitle":"Test PR Issue Link","messageBody":"","fileTypesAndContributionMap":{"functional-code":{"insertions":1,"deletions":1}}},{"hash":"006f8b8b8ac1183e57d40525448f8e536f15055d","isMergeCommit":false,"messageTitle":"Revert change","messageBody":"","fileTypesAndContributionMap":{"functional-code":{"insertions":1,"deletions":1}}},{"hash":"c8a7b81474f692f90e304188bbd254833bc4dcff","isMergeCommit":false,"messageTitle":"Update About Us","messageBody":"","fileTypesAndContributionMap":{"docs":{"insertions":11,"deletions":11}}},{"hash":"0510baf92467a79f0213106f58296776b4900f05","isMergeCommit":false,"messageTitle":"Delete other information in About Us","messageBody":"","fileTypesAndContributionMap":{"docs":{"insertions":1,"deletions":40}}},{"hash":"043b9b9b253b6aa53771e4e93dfe35fca4252768","isMergeCommit":false,"messageTitle":"Add photo to About Us","messageBody":"","fileTypesAndContributionMap":{"docs":{"insertions":1,"deletions":1}}},{"hash":"9587d8d0e1bd3091588ec5c39019b86c86a953bd","isMergeCommit":false,"messageTitle":"Update spelling","messageBody":"","fileTypesAndContributionMap":{"docs":{"insertions":1,"deletions":1}}},{"hash":"926144a150aeda5f1c5bb8990b2166e3b3c75cf4","isMergeCommit":true,"messageTitle":"Merge branch \u0027master\u0027 into About-Us","messageBody":"","fileTypesAndContributionMap":{}},{"hash":"d6651b385428b0784badbcf024719cc635c597d5","isMergeCommit":true,"messageTitle":"Merge pull request #29 from kimberlytmq/About-Us","messageBody":"Update About Us","fileTypesAndContributionMap":{}}]},{"date":"2024-10-03","commitResults":[{"hash":"a5d7a2579658bae2a9910f67af8b8d4dac87cbb8","isMergeCommit":false,"messageTitle":"Add target user, value proposition, and user stories to developer guide","messageBody":"","fileTypesAndContributionMap":{"docs":{"insertions":22,"deletions":15}}}]},{"date":"2024-10-05","commitResults":[{"hash":"31501f73511abce9adc544c37ac6c24255f727d8","isMergeCommit":true,"messageTitle":"Merge pull request #49 from kimberlytmq/add-target-user","messageBody":"Add target user, value proposition, and user stories to developer guide","fileTypesAndContributionMap":{}}]},{"date":"2024-10-11","commitResults":[{"hash":"850b52b68d7af129d03d2588790ee5f1f0176c63","isMergeCommit":false,"messageTitle":"Add telegram handle feature","messageBody":"","fileTypesAndContributionMap":{"functional-code":{"insertions":194,"deletions":41}}},{"hash":"3fa88b4b8bf75ab29b6fcdc1e796b6993fee85bc","isMergeCommit":false,"messageTitle":"Update import statements","messageBody":"","fileTypesAndContributionMap":{"functional-code":{"insertions":29,"deletions":5}}},{"hash":"baaaff63ee8a5ac4ecd6801f7ff6d4c7aad1c360","isMergeCommit":false,"messageTitle":"Fix import issue","messageBody":"","fileTypesAndContributionMap":{"functional-code":{"insertions":6,"deletions":1}}},{"hash":"62fedb29d1d4bf3bba7bbd83eb2951ff0d6c452d","isMergeCommit":true,"messageTitle":"Merge branch \u0027master\u0027 into Add-Telegram-Handle","messageBody":"","fileTypesAndContributionMap":{}},{"hash":"14d4fd71ec6cd791028cc3995a64cf07d756f22a","isMergeCommit":false,"messageTitle":"Remove trailing whitespace","messageBody":"","fileTypesAndContributionMap":{"docs":{"insertions":6,"deletions":6}}},{"hash":"67dfe2bac0ac5ef7c1206fe2df208bba7e0a7521","isMergeCommit":false,"messageTitle":"Remove address imports","messageBody":"","fileTypesAndContributionMap":{"functional-code":{"insertions":0,"deletions":6}}},{"hash":"6a12cb47555c8f466e2bab76125d6e56d6995c7a","isMergeCommit":false,"messageTitle":"Remove trailing whitespace","messageBody":"","fileTypesAndContributionMap":{"functional-code":{"insertions":1,"deletions":1}}},{"hash":"344917f86514e06a12abc8c112bfde23673c4f0d","isMergeCommit":false,"messageTitle":"Resolve conflict issues with address command removal","messageBody":"","fileTypesAndContributionMap":{"functional-code":{"insertions":1,"deletions":1}}},{"hash":"07b6c386af73a0de1af3efff51c5cff8845cea4e","isMergeCommit":false,"messageTitle":"Fix checkstyle errors","messageBody":"","fileTypesAndContributionMap":{"functional-code":{"insertions":42,"deletions":30}}},{"hash":"15cacf2f4208bd15743e4e7e575b74e8c7c0e4b6","isMergeCommit":false,"messageTitle":"Fix checkstyle errors","messageBody":"","fileTypesAndContributionMap":{"functional-code":{"insertions":2,"deletions":2},"test-code":{"insertions":2,"deletions":1}}},{"hash":"f02a6179765ada3e96d0a03503df0506651fe750","isMergeCommit":false,"messageTitle":"Fix person test case","messageBody":"","fileTypesAndContributionMap":{"test-code":{"insertions":2,"deletions":1}}}]},{"date":"2024-10-15","commitResults":[{"hash":"5e99cfda4719506edb1e983a549db8534714ab2c","isMergeCommit":false,"messageTitle":"Update User Guide commands","messageBody":"","fileTypesAndContributionMap":{"docs":{"insertions":13,"deletions":12}}},{"hash":"0dd2f8931a11dbcb84d17b67d9ec4b216d524b98","isMergeCommit":false,"messageTitle":"Revert \"Update User Guide commands\"","messageBody":"This reverts commit 5e99cfda4719506edb1e983a549db8534714ab2c.\n","fileTypesAndContributionMap":{"docs":{"insertions":12,"deletions":13}}},{"hash":"637b05101a23abf9d4413bd5944cec32b6e15a07","isMergeCommit":false,"messageTitle":"Update User Guide","messageBody":"","fileTypesAndContributionMap":{"docs":{"insertions":11,"deletions":10}}},{"hash":"f62f5650a89a3da124b1c01404f45307da423a61","isMergeCommit":false,"messageTitle":"Update User Guide","messageBody":"","fileTypesAndContributionMap":{"docs":{"insertions":1,"deletions":1}}},{"hash":"9094e025544d3b452a791b78ae6cabe8d0e65a82","isMergeCommit":false,"messageTitle":"Update help command link","messageBody":"","fileTypesAndContributionMap":{"functional-code":{"insertions":1,"deletions":1}}},{"hash":"8d48ba6f7f3cf1fa27167904c607d0e9976228b9","isMergeCommit":false,"messageTitle":"Update telegram field so that it only accepts valid telegram handles","messageBody":"","fileTypesAndContributionMap":{"functional-code":{"insertions":42,"deletions":6}}},{"hash":"7add8df110fb460d50b964a18a1962a6774a481d","isMergeCommit":false,"messageTitle":"Fix checktyle issues","messageBody":"","fileTypesAndContributionMap":{"functional-code":{"insertions":3,"deletions":3}}},{"hash":"f602ec363e72a424bbd698f1586c14cbdb7e4cbc","isMergeCommit":false,"messageTitle":"Fix test errors","messageBody":"","fileTypesAndContributionMap":{"functional-code":{"insertions":1,"deletions":2}}}]},{"date":"2024-10-17","commitResults":[{"hash":"e1e75bb7222e2cd0233eaff73b22a53304e3612f","isMergeCommit":false,"messageTitle":"Update user guide","messageBody":"","fileTypesAndContributionMap":{"docs":{"insertions":10,"deletions":8}}},{"hash":"e5f5aeec71aa4ed86833c87fe270db5625e87325","isMergeCommit":false,"messageTitle":"Updat User Guide","messageBody":"","fileTypesAndContributionMap":{"docs":{"insertions":3,"deletions":3}}},{"hash":"d674f02e670c2355ebbb48969d2a5fa5e3702fd4","isMergeCommit":true,"messageTitle":"Merge pull request #65 from kimberlytmq/help-command","messageBody":"Help command","fileTypesAndContributionMap":{}},{"hash":"c4b95fdf0689a6ae919db526b4a8ff7138d3c5ab","isMergeCommit":false,"messageTitle":"Update user guide to add contact type field","messageBody":"","fileTypesAndContributionMap":{"docs":{"insertions":5,"deletions":5}}},{"hash":"58d2e813fd501c7ef7b30fcc76026ce172f5c726","isMergeCommit":true,"messageTitle":"Merge pull request #76 from kimberlytmq/help-command","messageBody":"Update user guide to add contact type field","fileTypesAndContributionMap":{}}]}]},"authorFileTypeContributionMap":{"SlothyCat":{"docs":12,"functional-code":504,"test-code":23},"zienxu":{"docs":12,"functional-code":199,"test-code":12},"jtooya":{"docs":8,"functional-code":91,"test-code":42},"achl1012":{"docs":91,"functional-code":41,"test-code":222},"kimberlytmq":{"docs":36,"functional-code":236,"test-code":1}},"authorContributionVariance":{"SlothyCat":6127.9893,"zienxu":1206.1057,"jtooya":745.05115,"achl1012":10959.432,"kimberlytmq":5504.087},"authorDisplayNameMap":{"SlothyCat":"CS2103T-W12-3 YAP ..KANG","zienxu":"CS2103T-W12-3 ANG ..N XU","jtooya":"CS2103T-W12-3 JERE..N AN","achl1012":"CS2103T-W12-3 AMEL..LENG","kimberlytmq":"CS2103T-W12-3 TEO ..U QI"}}
